setup.py
switch/__init__.py
switch/switch.py
switch/test.py
switch_implement.egg-info/PKG-INFO
switch_implement.egg-info/SOURCES.txt
switch_implement.egg-info/dependency_links.txt
switch_implement.egg-info/top_level.txt