Metadata-Version: 1.0
Name: switch-implement
Version: 1
Summary: switch implementation with classes
Home-page: https://pypi.org/project/switch-implement/
Author: nacho00112
Author-email: tutohacker450@gmail.com
License: UNKNOWN
Platform: UNKNOWN
